visprompt/__init__.py
visprompt/gui/gui_image_utils.py
visprompt/gui/image_drawer.py
visprompt/segmentation/run_inference_sam_cli.py
visprompt/segmentation/run_inference_seggpt_cli.py
visprompt-0.1.5.dist-info/LICENSE
visprompt-0.1.5.dist-info/METADATA
visprompt-0.1.5.dist-info/WHEEL
visprompt-0.1.5.dist-info/RECORD
